README.md
setup.py
lightsteem/__init__.py
lightsteem/client.py
lightsteem/datastructures.py
lightsteem/exceptions.py
lightsteem.egg-info/PKG-INFO
lightsteem.egg-info/SOURCES.txt
lightsteem.egg-info/dependency_links.txt
lightsteem.egg-info/requires.txt
lightsteem.egg-info/top_level.txt
lightsteem/broadcast/__init__.py
lightsteem/broadcast/base58.py
lightsteem/broadcast/chains.py
lightsteem/broadcast/key_objects.py
lightsteem/broadcast/transaction_builder.py
lightsteem/broadcast/utils.py
lightsteem/helpers/__init__.py
lightsteem/helpers/account.py
lightsteem/helpers/amount.py
lightsteem/helpers/event_listener.py
lightsteem/helpers/rc.py
lightsteem/vendor/__init__.py
lightsteem/vendor/rc.py