Metadata-Version: 2.1
Name: lightsteem
Version: 0.1.3
Summary: A light python client to interact with the STEEM blockchain
Home-page: http://github.com/emre/lightsteem
Author: emre yilmaz
Author-email: mail@emreyilmaz.me
License: MIT
Platform: UNKNOWN
Provides-Extra: dev
